{"Id":0,"Char":"开","Pinyin":"kāi","Word":"拉开,开口,开工,开车,拨开,开放,离开,走开,开关,看开,开水,开会,开春,开门","Strokes":4,"Radical":"廾","Elements":"木","Big5":"開","Rank":0,"Paraphrase":"1.使关闭着的东西不再关闭；打开：～门。～锁。～箱子。不～口。\n2.打通；开辟：～路。～矿。墙上～了个窗口。～了三千亩水田。\n3.（合拢或连接的东西）展开；分离：桃树～花了。扣儿～了。两块木板没粘好，又～了。\n4.（河流）解冻：河～了。\n5.解除（封锁、禁令、限制等）：～戒。～禁。～斋。～释。\n6.发动或操纵（枪、炮、车、船、飞机、机器等）：～枪。～汽车。～拖拉机。火车～了。\n7.（队伍）开拔：昨天～来两团人，今天又～走了。\n8.开办：～工厂。～医院。\n9.开始：～工。～学。～演。\n10.姓。\n11.开金中含纯金量的计算单位（二十四开为纯金）：这条金项链是十八～的。[英karat]\n12.开尔文的简称。1开是水的三相点热力学温度的1/273.16。\n13.趋向动词。用在动词或形容词后。a）表示分开或离开：拉～。躲～。把门推～。窗户关得紧，打不～。b）表示容下：屋子小，人多了坐不～。这张大床，三个孩子也睡～了。c）表示扩大或扩展：喜讯传～了。d）表示开始并继续下去：下了两天雨，天就冷～了。天还没亮，大家就干～了。","Unicode":"\\u5f00","Guid":"8493205602379573013B8D3335981175"}